nonebot_plugin_PicaJm/__init__.py
nonebot_plugin_PicaJm/config.py
nonebot_plugin_PicaJm/pic2.py
nonebot_plugin_picajm-0.1.0.dist-info/LICENSE
nonebot_plugin_picajm-0.1.0.dist-info/METADATA
nonebot_plugin_picajm-0.1.0.dist-info/WHEEL
nonebot_plugin_picajm-0.1.0.dist-info/RECORD
