Metadata-Version: 2.3
Name: nonebot-plugin-PicaJm
Version: 0.1.0
Summary: 可以看pica和jm
License: GPL-3.0-only
Author: CCYellowStar
Requires-Python: >=3.9,<4
Classifier: License :: OSI Approved :: GNU General Public License v3 (GPLv3)
Classifier: Programming Language :: Python :: 3
Classifier: Programming Language :: Python :: 3.9
Classifier: Programming Language :: Python :: 3.10
Classifier: Programming Language :: Python :: 3.11
Classifier: Programming Language :: Python :: 3.12
Classifier: Programming Language :: Python :: 3.13
Requires-Dist: aiohttp (>=3.8.4)
Requires-Dist: fuzzywuzzy (>=0.18.0)
Requires-Dist: jmcomic (>=2.5.32)
Requires-Dist: nonebot2 (>=2.3.0)
Requires-Dist: python-levenshtein (>=0.26.1)
Requires-Dist: pyzipper (>=0.3.6)
Project-URL: Homepage, https://github.com/CCYellowStar2/nonebot-plugin-PicaJm
Project-URL: Repository, https://github.com/CCYellowStar2/nonebot-plugin-PicaJm
